donbest.py
donbest-1.0.2.dist-info/METADATA
donbest-1.0.2.dist-info/RECORD
donbest-1.0.2.dist-info/WHEEL
donbest-1.0.2.dist-info/top_level.txt
