Metadata-Version: 2.1
Name: donbest
Version: 1.0.2
Summary: An easy-to-use python wrapper for the Don Best Sports API
Home-page: https://github.com/mamcmanus/donbest.py
Author: Matthew McManus
Author-email: matt@rexmark.co
License: UNKNOWN
Platform: UNKNOWN
Classifier: Programming Language :: Python :: 3
Classifier: License :: OSI Approved :: MIT License
Classifier: Operating System :: OS Independent
Requires-Python: >=3
Requires-Dist: requests
